<annotation>
  <folder></folder>
  <filename>DSC07730.jpg</filename>
  <source>
    <database>Unknown</database>
    <annotation>Unknown</annotation>
    <image>Unknown</image>
  </source>
  <size>
    <width>576</width>
    <height>1024</height>
    <depth></depth>
  </size>
  <segmented>0</segmented>
  <object>
    <name>Canker</name>
    <truncated>0</truncated>
    <occluded>0</occluded>
    <difficult>0</difficult>
    <bndbox>
      <xmin>225.48</xmin>
      <ymin>580.69</ymin>
      <xmax>268.67</xmax>
      <ymax>659.82</ymax>
    </bndbox>
  </object>
  <object>
    <name>Canker</name>
    <truncated>0</truncated>
    <occluded>0</occluded>
    <difficult>0</difficult>
    <bndbox>
      <xmin>195.33</xmin>
      <ymin>451.12</ymin>
      <xmax>302.08</xmax>
      <ymax>580.77</ymax>
    </bndbox>
  </object>
</annotation>
