<annotation>
  <folder>IMG</folder>
  <filename>IMG_1901.jpg</filename>
  <source>
    <database>Unknown</database>
    <annotation>Unknown</annotation>
    <image>Unknown</image>
  </source>
  <size>
    <width>768</width>
    <height>1024</height>
    <depth></depth>
  </size>
  <segmented>0</segmented>
  <object>
    <name>Rust</name>
    <truncated>0</truncated>
    <occluded>0</occluded>
    <difficult>0</difficult>
    <bndbox>
      <xmin>183.2</xmin>
      <ymin>665.4</ymin>
      <xmax>258.55</xmax>
      <ymax>780.04</ymax>
    </bndbox>
  </object>
  <object>
    <name>Rust</name>
    <truncated>0</truncated>
    <occluded>0</occluded>
    <difficult>0</difficult>
    <bndbox>
      <xmin>487.19</xmin>
      <ymin>335.2</ymin>
      <xmax>754.55</xmax>
      <ymax>549.94</ymax>
    </bndbox>
  </object>
  <object>
    <name>Rust</name>
    <truncated>0</truncated>
    <occluded>0</occluded>
    <difficult>0</difficult>
    <bndbox>
      <xmin>131.17</xmin>
      <ymin>301.97</ymin>
      <xmax>429.0</xmax>
      <ymax>601.19</ymax>
    </bndbox>
  </object>
  <object>
    <name>Rust</name>
    <truncated>0</truncated>
    <occluded>0</occluded>
    <difficult>0</difficult>
    <bndbox>
      <xmin>372.21</xmin>
      <ymin>497.3</ymin>
      <xmax>530.13</xmax>
      <ymax>808.99</ymax>
    </bndbox>
  </object>
  <object>
    <name>Rust</name>
    <truncated>0</truncated>
    <occluded>0</occluded>
    <difficult>0</difficult>
    <bndbox>
      <xmin>0.42</xmin>
      <ymin>597.26</ymin>
      <xmax>105.44</xmax>
      <ymax>811.3</ymax>
    </bndbox>
  </object>
  <object>
    <name>Rust</name>
    <truncated>0</truncated>
    <occluded>0</occluded>
    <difficult>0</difficult>
    <bndbox>
      <xmin>287.41</xmin>
      <ymin>598.54</ymin>
      <xmax>373.99</xmax>
      <ymax>670.69</ymax>
    </bndbox>
  </object>
  <object>
    <name>Rust</name>
    <truncated>0</truncated>
    <occluded>0</occluded>
    <difficult>0</difficult>
    <bndbox>
      <xmin>249.28</xmin>
      <ymin>850.93</ymin>
      <xmax>332.79</xmax>
      <ymax>970.51</ymax>
    </bndbox>
  </object>
  <object>
    <name>Rust</name>
    <truncated>0</truncated>
    <occluded>0</occluded>
    <difficult>0</difficult>
    <bndbox>
      <xmin>379.55</xmin>
      <ymin>793.48</ymin>
      <xmax>507.15</xmax>
      <ymax>874.98</ymax>
    </bndbox>
  </object>
  <object>
    <name>Rust</name>
    <truncated>0</truncated>
    <occluded>0</occluded>
    <difficult>0</difficult>
    <bndbox>
      <xmin>259.97</xmin>
      <ymin>703.29</ymin>
      <xmax>342.81</xmax>
      <ymax>812.85</ymax>
    </bndbox>
  </object>
  <object>
    <name>Rust</name>
    <truncated>0</truncated>
    <occluded>0</occluded>
    <difficult>0</difficult>
    <bndbox>
      <xmin>400.34</xmin>
      <ymin>251.61</ymin>
      <xmax>512.89</xmax>
      <ymax>450.75</ymax>
    </bndbox>
  </object>
  <object>
    <name>Rust</name>
    <truncated>0</truncated>
    <occluded>0</occluded>
    <difficult>0</difficult>
    <bndbox>
      <xmin>685.09</xmin>
      <ymin>199.66</ymin>
      <xmax>753.39</xmax>
      <ymax>304.52</ymax>
    </bndbox>
  </object>
  <object>
    <name>Rust</name>
    <truncated>0</truncated>
    <occluded>0</occluded>
    <difficult>0</difficult>
    <bndbox>
      <xmin>51.54</xmin>
      <ymin>390.64</ymin>
      <xmax>149.07</xmax>
      <ymax>597.07</ymax>
    </bndbox>
  </object>
</annotation>
