<annotation>
  <folder>IMG</folder>
  <filename>IMG_20211104_155900.jpg</filename>
  <source>
    <database>Unknown</database>
    <annotation>Unknown</annotation>
    <image>Unknown</image>
  </source>
  <size>
    <width>461</width>
    <height>1024</height>
    <depth></depth>
  </size>
  <segmented>0</segmented>
  <object>
    <name>Pepper yellow leaf</name>
    <truncated>0</truncated>
    <occluded>0</occluded>
    <difficult>0</difficult>
    <bndbox>
      <xmin>249.02</xmin>
      <ymin>370.0</ymin>
      <xmax>436.58</xmax>
      <ymax>667.4</ymax>
    </bndbox>
  </object>
  <object>
    <name>Pepper yellow leaf</name>
    <truncated>0</truncated>
    <occluded>0</occluded>
    <difficult>0</difficult>
    <bndbox>
      <xmin>139.18</xmin>
      <ymin>155.4</ymin>
      <xmax>237.19</xmax>
      <ymax>309.17</ymax>
    </bndbox>
  </object>
  <object>
    <name>Pepper yellow leaf</name>
    <truncated>0</truncated>
    <occluded>0</occluded>
    <difficult>0</difficult>
    <bndbox>
      <xmin>91.87</xmin>
      <ymin>299.03</ymin>
      <xmax>252.4</xmax>
      <ymax>560.95</ymax>
    </bndbox>
  </object>
</annotation>
